README.txt
setup.py
docs/HISTORY.txt
docs/INSTALL.txt
docs/LICENSE.GPL
docs/LICENSE.txt
medialog/__init__.py
medialog/__init__.pyc
medialog.portlet.sitemap.egg-info/PKG-INFO
medialog.portlet.sitemap.egg-info/SOURCES.txt
medialog.portlet.sitemap.egg-info/dependency_links.txt
medialog.portlet.sitemap.egg-info/entry_points.txt
medialog.portlet.sitemap.egg-info/namespace_packages.txt
medialog.portlet.sitemap.egg-info/not-zip-safe
medialog.portlet.sitemap.egg-info/requires.txt
medialog.portlet.sitemap.egg-info/top_level.txt
medialog/portlet/__init__.py
medialog/portlet/__init__.pyc
medialog/portlet/sitemap/__init__.py
medialog/portlet/sitemap/__init__.pyc
medialog/portlet/sitemap/configure.zcml
medialog/portlet/sitemap/sitemapportlet.pt
medialog/portlet/sitemap/sitemapportlet.py
medialog/portlet/sitemap/sitemapportlet.pyc
medialog/portlet/sitemap/skins.zcml
medialog/portlet/sitemap/version.txt
medialog/portlet/sitemap/profiles/default/jsregistry.xml
medialog/portlet/sitemap/profiles/default/metadata.xml
medialog/portlet/sitemap/profiles/default/portlets.xml
medialog/portlet/sitemap/profiles/default/skins.xml
medialog/portlet/sitemap/skins/sitemapportlet/jq-sitemap.js
medialog/portlet/sitemap/skins/sitemapportlet/jquery-ui-accordion.js
medialog/portlet/sitemap/tests/__init__.py
medialog/portlet/sitemap/tests/base.py
medialog/portlet/sitemap/tests/test_portlet.py