Metadata-Version: 1.0
Name: medialog.portlet.sitemap
Version: 4.0a2
Summary: Shows the whole sitemap in a portlet. For Plone 4
Home-page: http://medialog.no
Author: Espen Moe-NIlssen
Author-email: espen@medialog.no
License: GPL
Platform: UNKNOWN
Classifier: Framework :: Plone
Classifier: Programming Language :: Python
Classifier: Topic :: Software Development :: Libraries :: Python Modules
